topic_benchmark/__init__.py
topic_benchmark/__main__.py
topic_benchmark/base.py
topic_benchmark/benchmark.py
topic_benchmark/cli.py
topic_benchmark/datasets/__init__.py
topic_benchmark/datasets/arxiv_ml.py
topic_benchmark/datasets/bbc_news.py
topic_benchmark/datasets/newsgroups.py
topic_benchmark/datasets/stackexchange.py
topic_benchmark/datasets/wiki_medical.py
topic_benchmark/defaults.py
topic_benchmark/encoders/__init__.py
topic_benchmark/encoders/e5_encoders.py
topic_benchmark/metrics/__init__.py
topic_benchmark/metrics/diversity.py
topic_benchmark/metrics/npmi.py
topic_benchmark/metrics/wec.py
topic_benchmark/models/__init__.py
topic_benchmark/models/_ecrtm.py
topic_benchmark/models/bertopic.py
topic_benchmark/models/classical.py
topic_benchmark/models/ecrtm.py
topic_benchmark/models/top2vec.py
topic_benchmark/models/turftopic.py
topic_benchmark/registries.py
topic_benchmark/table.py
topic_benchmark/utils.py
topic_benchmark-0.5.0.dist-info/LICENSE
topic_benchmark-0.5.0.dist-info/METADATA
topic_benchmark-0.5.0.dist-info/WHEEL
topic_benchmark-0.5.0.dist-info/RECORD
